termcheat/__init__.py
termcheat/app.py
termcheat/commands.yaml
term_cheat-0.1.12.dist-info/LICENSE
term_cheat-0.1.12.dist-info/METADATA
term_cheat-0.1.12.dist-info/WHEEL
term_cheat-0.1.12.dist-info/entry_points.txt
term_cheat-0.1.12.dist-info/top_level.txt
term_cheat-0.1.12.dist-info/RECORD
