Metadata-Version: 2.1
Name: term-cheat
Version: 0.1.12
Summary: A text base UI for collecting and finding termial commands.
Home-page: https://github.com/select/term-cheat
Author: @select@github.com
Author-email: falko@webpgr.com
License: UNKNOWN
Platform: UNKNOWN
Classifier: Programming Language :: Python :: 3
Classifier: License :: OSI Approved :: MIT License
Classifier: Operating System :: POSIX :: Linux
Requires-Dist: urwid
Requires-Dist: fuzzywuzzy
Requires-Dist: pyyaml
Requires-Dist: appdirs
Requires-Dist: python-Levenshtein
